common/README.md
common/__init__.py
common/requirements.txt
common/run_tests.sh
common/lib/__init__.py
common/lib/components/__init__.py
common/lib/components/cpu/__init__.py
common/lib/components/cpu/common.py
common/lib/components/cpu/cpudescriptor.py
common/lib/components/cpu/cpuinfo.py
common/lib/components/cpu/cpumatcher.py
common/lib/components/cpu/cpurequirements.py
common/lib/components/cpu/cpustatus.py
common/lib/components/cpu/tests/__init__.py
common/lib/components/cpu/tests/test_coresstatus.py
common/lib/components/cpu/tests/test_corestatus.py
common/lib/components/cpu/tests/test_cpudescriptor.py
common/lib/components/cpu/tests/test_cpumatcher.py
common/lib/components/cpu/tests/test_cpustatus.py
common/lib/components/memory/__init__.py
common/lib/components/memory/memdescriptor.py
common/lib/components/memory/memmatcher.py
common/lib/components/memory/memrequirements.py
common/lib/components/memory/memstatus.py
common/lib/components/misc/__init__.py
common/lib/components/misc/miscmatcher.py
common/lib/components/misc/miscrequirements.py
common/lib/components/misc/miscstatus.py
common/lib/components/net/__init__.py
common/lib/components/net/netmatcher.py
common/lib/components/net/netrequirements.py
common/lib/components/net/netspeed.py
common/lib/components/net/netstatus.py
common/lib/components/pcidev/__init__.py
common/lib/components/pcidev/pcimatcher.py
common/lib/components/pcidev/pcirequirements.py
common/lib/components/pcidev/pcistatus.py
common/lib/components/pcidev/tests/__init__.py
common/lib/components/pcidev/tests/test_pciaddress.py
common/lib/components/pcidev/tests/test_pcidevice.py
common/lib/components/pcidev/tests/test_pcimatcher.py
common/lib/components/pcidev/tests/test_pcirequirements.py
common/lib/components/pcidev/tests/test_pciscanner.py
common/lib/components/pcidev/tests/test_pcistatus.py
common/lib/system/__init__.py
common/lib/system/systemmatcher.py
common/lib/system/systemrequirements.py
common/lib/system/systemstatus.py
elemento_cli-0.2.1.dist-info/METADATA
elemento_cli-0.2.1.dist-info/WHEEL
elemento_cli-0.2.1.dist-info/top_level.txt
elemento_cli-0.2.1.dist-info/RECORD
