Metadata-Version: 2.1
Name: elemento-cli
Version: 0.2.1
Summary: CLI for Elemento
Home-page: https://elemento.cloud
Author: Elemento
Author-email: hello@elemento.cloud
License: GPL
Requires-Python: >=3.9
Requires-Dist: argparse
Requires-Dist: argcomplete
Requires-Dist: tabulate
Requires-Dist: jsonpickle
Requires-Dist: pyasyncore
Requires-Dist: pwinput
Requires-Dist: requests
Requires-Dist: si-prefix ===1.0
Requires-Dist: urllib3 ==1.26.6
